confetti/__init__.py
confetti/admin.py
confetti/api.py
confetti/apps.py
confetti/conf.py
confetti/defaults.py
confetti/models.py
confetti/openapi.py
confetti/responses.py
confetti/seed.py
confetti/serializers.py
confetti/signals.py
confetti/swagger_compat.py
confetti/urls.py
confetti/validators.py
confetti/views.py
confetti/management/__init__.py
confetti/management/commands/__init__.py
confetti/management/commands/confetti_seed.py
confetti/management/commands/confetti_sync.py
confetti/migrations/0001_initial.py
confetti/migrations/__init__.py
django_confetti-0.3.0.dist-info/licenses/LICENSE
django_confetti-0.3.0.dist-info/METADATA
django_confetti-0.3.0.dist-info/WHEEL
django_confetti-0.3.0.dist-info/top_level.txt
django_confetti-0.3.0.dist-info/RECORD
