Metadata-Version: 2.4
Name: django-confetti
Version: 0.3.0
Summary: Config & feature settings for Django: global/user overrides, cache, API, seeding.
Author-email: Sapp <sapp1507@gmail.com>
License: MIT
Keywords: django,settings,feature-flags,config
Classifier: Framework :: Django
Classifier: Framework :: Django :: 3.2
Classifier: Framework :: Django :: 4
Classifier: Programming Language :: Python :: 3
Classifier: License :: OSI Approved :: MIT License
Classifier: Intended Audience :: Developers
Classifier: Topic :: Software Development :: Libraries :: Python Modules
Requires-Python: >=3.10
License-File: LICENSE
Requires-Dist: Django>=3.2
Provides-Extra: drf
Requires-Dist: djangorestframework>=3.14; extra == "drf"
Provides-Extra: docs
Requires-Dist: drf-yasg>=1.21.5; extra == "docs"
Dynamic: license-file
